{"100148":[75101,"{\"town\":\"Paris 1er Arrondissement\",\"update\":\"2026-02-03T09:13:16+01:00\",\"datetime\":\"2026-02-03T13:00:00+0100\",\"rr10\":4.8,\"rr1\":7,\"weather\":210,\"temp2m\":10,\"wind10m\":15,\"gust10m\":38,\"dirwind10m\":217,\"probarain\":100,\"probafog\":0,\"probafrost\":0,\"probawind70\":0,\"probawind100\":0,\"gustx\":40,\"iso0\":\"\",\"datetime_1\":\"2026-02-04T13:00:00+0100\",\"rr10_1\":0,\"rr1_1\":0,\"weather_1\":1,\"temp2m_1\":11,\"wind10m_1\":10,\"gust10m_1\":30,\"dirwind10m_1\":115,\"probarain_1\":0,\"probafog_1\":0,\"probafrost_1\":0,\"probawind70_1\":0,\"probawind100_1\":0,\"gustx_1\":30,\"iso0_1\":\"\",\"station\":\"Paris (75)\",\"temperature\":[\"8.9\",\"\\u00b0C\"],\"barometer\":[\"991.6\",\"hPa\"],\"rainfall\":[\"0.2\",\"mm\"],\"solar_radiation\":[\"58\",\"W\/m\\u00b2\"],\"wind_speed\":[\"25.6\",\"km\/h\"],\"windchill\":[\"\",\"\"],\"windgust_speed\":[\"\",\"\"],\"outside_humidity\":[\"93\",\"%\"],\"sunrise\":\"08:15:00\",\"sunset\":\"17:52:00\",\"diffday\":3,\"moon_age\":15.9,\"moon_phase\":\"Pleine lune\"}"],"142140":[75101,"{\"town\":\"Paris 1er Arrondissement\",\"update\":\"2026-02-04T14:10:23+01:00\",\"datetime\":\"2026-02-04T13:00:00+0100\",\"rr10\":0,\"rr1\":0,\"weather\":2,\"temp2m\":12,\"wind10m\":15,\"gust10m\":44,\"dirwind10m\":127,\"probarain\":10,\"probafog\":0,\"probafrost\":0,\"probawind70\":0,\"probawind100\":0,\"gustx\":44,\"iso0\":\"\",\"datetime_1\":\"2026-02-05T13:00:00+0100\",\"rr10_1\":0.1,\"rr1_1\":0.1,\"weather_1\":10,\"temp2m_1\":12,\"wind10m_1\":10,\"gust10m_1\":29,\"dirwind10m_1\":178,\"probarain_1\":40,\"probafog_1\":10,\"probafrost_1\":0,\"probawind70_1\":0,\"probawind100_1\":0,\"gustx_1\":29,\"iso0_1\":\"\",\"station\":\"Paris (75)\",\"temperature\":[\"12.2\",\"\\u00b0C\"],\"barometer\":[\"989.4\",\"hPa\"],\"rainfall\":[\"0.0\",\"mm\"],\"solar_radiation\":[\"367\",\"W\/m\\u00b2\"],\"wind_speed\":[\"44.6\",\"km\/h\"],\"windchill\":[\"\",\"\"],\"windgust_speed\":[\"\",\"\"],\"outside_humidity\":[\"61\",\"%\"],\"sunrise\":\"08:14:00\",\"sunset\":\"17:54:00\",\"diffday\":4,\"moon_age\":16.9,\"moon_phase\":\"Lune gibbeuse d\\u00e9croissante\"}"],"151142":[75101,"{\"town\":\"Paris 1er Arrondissement\",\"update\":\"2026-02-04T15:10:40+01:00\",\"datetime\":\"2026-02-04T13:00:00+0100\",\"rr10\":0,\"rr1\":0,\"weather\":2,\"temp2m\":12,\"wind10m\":15,\"gust10m\":44,\"dirwind10m\":127,\"probarain\":10,\"probafog\":0,\"probafrost\":0,\"probawind70\":0,\"probawind100\":0,\"gustx\":44,\"iso0\":\"\",\"datetime_1\":\"2026-02-05T13:00:00+0100\",\"rr10_1\":0.1,\"rr1_1\":0.1,\"weather_1\":10,\"temp2m_1\":12,\"wind10m_1\":10,\"gust10m_1\":29,\"dirwind10m_1\":178,\"probarain_1\":40,\"probafog_1\":10,\"probafrost_1\":0,\"probawind70_1\":0,\"probawind100_1\":0,\"gustx_1\":29,\"iso0_1\":\"\",\"station\":\"Paris (75)\",\"temperature\":[\"11.7\",\"\\u00b0C\"],\"barometer\":[\"988.7\",\"hPa\"],\"rainfall\":[\"0.0\",\"mm\"],\"solar_radiation\":[\"61\",\"W\/m\\u00b2\"],\"wind_speed\":[\"30.6\",\"km\/h\"],\"windchill\":[\"\",\"\"],\"windgust_speed\":[\"\",\"\"],\"outside_humidity\":[\"64\",\"%\"],\"sunrise\":\"08:14:00\",\"sunset\":\"17:54:00\",\"diffday\":4,\"moon_age\":16.9,\"moon_phase\":\"Lune gibbeuse d\\u00e9croissante\"}"],"163656":[75101,"{\"town\":\"Paris 1er Arrondissement\",\"update\":\"2026-02-04T16:10:23+01:00\",\"datetime\":\"2026-02-04T19:00:00+0100\",\"rr10\":0,\"rr1\":0,\"weather\":3,\"temp2m\":10,\"wind10m\":15,\"gust10m\":39,\"dirwind10m\":131,\"probarain\":30,\"probafog\":0,\"probafrost\":0,\"probawind70\":0,\"probawind100\":0,\"gustx\":39,\"iso0\":\"\",\"datetime_1\":\"2026-02-05T19:00:00+0100\",\"rr10_1\":0.7,\"rr1_1\":0.8,\"weather_1\":10,\"temp2m_1\":10,\"wind10m_1\":5,\"gust10m_1\":29,\"dirwind10m_1\":125,\"probarain_1\":90,\"probafog_1\":10,\"probafrost_1\":0,\"probawind70_1\":0,\"probawind100_1\":0,\"gustx_1\":29,\"iso0_1\":\"\",\"station\":\"Paris (75)\",\"temperature\":[\"11.6\",\"\\u00b0C\"],\"barometer\":[\"988.2\",\"hPa\"],\"rainfall\":[\"0.0\",\"mm\"],\"solar_radiation\":[\"44\",\"W\/m\\u00b2\"],\"wind_speed\":[\"36.7\",\"km\/h\"],\"windchill\":[\"\",\"\"],\"windgust_speed\":[\"\",\"\"],\"outside_humidity\":[\"63\",\"%\"],\"sunrise\":\"08:14:00\",\"sunset\":\"17:54:00\",\"diffday\":4,\"moon_age\":16.9,\"moon_phase\":\"Lune gibbeuse d\\u00e9croissante\"}"],"212154":[75101,"{\"town\":\"Paris 1er Arrondissement\",\"update\":\"2026-02-04T16:10:23+01:00\",\"datetime\":\"2026-02-04T19:00:00+0100\",\"rr10\":0,\"rr1\":0,\"weather\":3,\"temp2m\":10,\"wind10m\":15,\"gust10m\":39,\"dirwind10m\":131,\"probarain\":30,\"probafog\":0,\"probafrost\":0,\"probawind70\":0,\"probawind100\":0,\"gustx\":39,\"iso0\":\"\",\"datetime_1\":\"2026-02-05T19:00:00+0100\",\"rr10_1\":0.7,\"rr1_1\":0.8,\"weather_1\":10,\"temp2m_1\":10,\"wind10m_1\":5,\"gust10m_1\":29,\"dirwind10m_1\":125,\"probarain_1\":90,\"probafog_1\":10,\"probafrost_1\":0,\"probawind70_1\":0,\"probawind100_1\":0,\"gustx_1\":29,\"iso0_1\":\"\",\"station\":\"Paris (75)\",\"temperature\":[\"9.7\",\"\\u00b0C\"],\"barometer\":[\"986.9\",\"hPa\"],\"rainfall\":[\"0.0\",\"mm\"],\"solar_radiation\":[\"0\",\"W\/m\\u00b2\"],\"wind_speed\":[\"38.9\",\"km\/h\"],\"windchill\":[\"\",\"\"],\"windgust_speed\":[\"\",\"\"],\"outside_humidity\":[\"67\",\"%\"],\"sunrise\":\"08:14:00\",\"sunset\":\"17:54:00\",\"diffday\":4,\"moon_age\":16.9,\"moon_phase\":\"Lune gibbeuse d\\u00e9croissante\"}"],"105216":[75101,"{\"town\":\"Paris 1er Arrondissement\",\"update\":\"2026-02-05T09:12:37+01:00\",\"datetime\":\"2026-02-05T13:00:00+0100\",\"rr10\":0.2,\"rr1\":0.3,\"weather\":10,\"temp2m\":12,\"wind10m\":10,\"gust10m\":30,\"dirwind10m\":174,\"probarain\":50,\"probafog\":10,\"probafrost\":0,\"probawind70\":0,\"probawind100\":0,\"gustx\":30,\"iso0\":\"\",\"datetime_1\":\"2026-02-06T13:00:00+0100\",\"rr10_1\":0.2,\"rr1_1\":0.2,\"weather_1\":40,\"temp2m_1\":12,\"wind10m_1\":15,\"gust10m_1\":41,\"dirwind10m_1\":229,\"probarain_1\":50,\"probafog_1\":0,\"probafrost_1\":0,\"probawind70_1\":0,\"probawind100_1\":0,\"gustx_1\":41,\"iso0_1\":\"\",\"station\":\"Paris (75)\",\"temperature\":[\"9.2\",\"\\u00b0C\"],\"barometer\":[\"985.5\",\"hPa\"],\"rainfall\":[\"0.0\",\"mm\"],\"solar_radiation\":[\"108\",\"W\/m\\u00b2\"],\"wind_speed\":[\"29.5\",\"km\/h\"],\"windchill\":[\"\",\"\"],\"windgust_speed\":[\"\",\"\"],\"outside_humidity\":[\"92\",\"%\"],\"sunrise\":\"08:13:00\",\"sunset\":\"17:56:00\",\"diffday\":3,\"moon_age\":17.9,\"moon_phase\":\"Lune gibbeuse d\\u00e9croissante\"}"],"110406":[75101,"{\"town\":\"Paris 1er Arrondissement\",\"update\":\"2026-02-05T09:12:37+01:00\",\"datetime\":\"2026-02-05T13:00:00+0100\",\"rr10\":0.2,\"rr1\":0.3,\"weather\":10,\"temp2m\":12,\"wind10m\":10,\"gust10m\":30,\"dirwind10m\":174,\"probarain\":50,\"probafog\":10,\"probafrost\":0,\"probawind70\":0,\"probawind100\":0,\"gustx\":30,\"iso0\":\"\",\"datetime_1\":\"2026-02-06T13:00:00+0100\",\"rr10_1\":0.2,\"rr1_1\":0.2,\"weather_1\":40,\"temp2m_1\":12,\"wind10m_1\":15,\"gust10m_1\":41,\"dirwind10m_1\":229,\"probarain_1\":50,\"probafog_1\":0,\"probafrost_1\":0,\"probawind70_1\":0,\"probawind100_1\":0,\"gustx_1\":41,\"iso0_1\":\"\",\"station\":\"Paris (75)\",\"temperature\":[\"9.8\",\"\\u00b0C\"],\"barometer\":[\"985.4\",\"hPa\"],\"rainfall\":[\"0.0\",\"mm\"],\"solar_radiation\":[\"138\",\"W\/m\\u00b2\"],\"wind_speed\":[\"29.9\",\"km\/h\"],\"windchill\":[\"\",\"\"],\"windgust_speed\":[\"\",\"\"],\"outside_humidity\":[\"90\",\"%\"],\"sunrise\":\"08:13:00\",\"sunset\":\"17:56:00\",\"diffday\":3,\"moon_age\":17.9,\"moon_phase\":\"Lune gibbeuse d\\u00e9croissante\"}"],"121546":[75101,"{\"town\":\"Paris 1er Arrondissement\",\"update\":\"2026-02-05T09:12:37+01:00\",\"datetime\":\"2026-02-05T13:00:00+0100\",\"rr10\":0.2,\"rr1\":0.3,\"weather\":10,\"temp2m\":12,\"wind10m\":10,\"gust10m\":30,\"dirwind10m\":174,\"probarain\":50,\"probafog\":10,\"probafrost\":0,\"probawind70\":0,\"probawind100\":0,\"gustx\":30,\"iso0\":\"\",\"datetime_1\":\"2026-02-06T13:00:00+0100\",\"rr10_1\":0.2,\"rr1_1\":0.2,\"weather_1\":40,\"temp2m_1\":12,\"wind10m_1\":15,\"gust10m_1\":41,\"dirwind10m_1\":229,\"probarain_1\":50,\"probafog_1\":0,\"probafrost_1\":0,\"probawind70_1\":0,\"probawind100_1\":0,\"gustx_1\":41,\"iso0_1\":\"\",\"station\":\"Paris (75)\",\"temperature\":[\"9.9\",\"\\u00b0C\"],\"barometer\":[\"985.3\",\"hPa\"],\"rainfall\":[\"0.0\",\"mm\"],\"solar_radiation\":[\"107\",\"W\/m\\u00b2\"],\"wind_speed\":[\"29.5\",\"km\/h\"],\"windchill\":[\"\",\"\"],\"windgust_speed\":[\"\",\"\"],\"outside_humidity\":[\"90\",\"%\"],\"sunrise\":\"08:13:00\",\"sunset\":\"17:56:00\",\"diffday\":3,\"moon_age\":17.9,\"moon_phase\":\"Lune gibbeuse d\\u00e9croissante\"}"],"134050":[75101,"{\"town\":\"Paris 1er Arrondissement\",\"update\":\"2026-02-05T09:12:37+01:00\",\"datetime\":\"2026-02-05T13:00:00+0100\",\"rr10\":0.2,\"rr1\":0.3,\"weather\":10,\"temp2m\":12,\"wind10m\":10,\"gust10m\":30,\"dirwind10m\":174,\"probarain\":50,\"probafog\":10,\"probafrost\":0,\"probawind70\":0,\"probawind100\":0,\"gustx\":30,\"iso0\":\"\",\"datetime_1\":\"2026-02-06T13:00:00+0100\",\"rr10_1\":0.2,\"rr1_1\":0.2,\"weather_1\":40,\"temp2m_1\":12,\"wind10m_1\":15,\"gust10m_1\":41,\"dirwind10m_1\":229,\"probarain_1\":50,\"probafog_1\":0,\"probafrost_1\":0,\"probawind70_1\":0,\"probawind100_1\":0,\"gustx_1\":41,\"iso0_1\":\"\",\"station\":\"Paris (75)\",\"temperature\":[\"11.3\",\"\\u00b0C\"],\"barometer\":[\"984.7\",\"hPa\"],\"rainfall\":[\"0.0\",\"mm\"],\"solar_radiation\":[\"300\",\"W\/m\\u00b2\"],\"wind_speed\":[\"32.8\",\"km\/h\"],\"windchill\":[\"\",\"\"],\"windgust_speed\":[\"\",\"\"],\"outside_humidity\":[\"84\",\"%\"],\"sunrise\":\"08:13:00\",\"sunset\":\"17:56:00\",\"diffday\":3,\"moon_age\":17.9,\"moon_phase\":\"Lune gibbeuse d\\u00e9croissante\"}"],"155451":[75101,"{\"town\":\"Paris 1er Arrondissement\",\"update\":\"2026-02-05T15:10:23+01:00\",\"datetime\":\"2026-02-05T13:00:00+0100\",\"rr10\":0,\"rr1\":0,\"weather\":10,\"temp2m\":13,\"wind10m\":10,\"gust10m\":31,\"dirwind10m\":155,\"probarain\":50,\"probafog\":0,\"probafrost\":0,\"probawind70\":0,\"probawind100\":0,\"gustx\":31,\"iso0\":\"\",\"datetime_1\":\"2026-02-06T13:00:00+0100\",\"rr10_1\":0.2,\"rr1_1\":0.2,\"weather_1\":40,\"temp2m_1\":12,\"wind10m_1\":15,\"gust10m_1\":43,\"dirwind10m_1\":228,\"probarain_1\":60,\"probafog_1\":0,\"probafrost_1\":0,\"probawind70_1\":0,\"probawind100_1\":0,\"gustx_1\":43,\"iso0_1\":\"\",\"station\":\"Paris (75)\",\"temperature\":[\"11.9\",\"\\u00b0C\"],\"barometer\":[\"984.7\",\"hPa\"],\"rainfall\":[\"0.0\",\"mm\"],\"solar_radiation\":[\"36\",\"W\/m\\u00b2\"],\"wind_speed\":[\"24.8\",\"km\/h\"],\"windchill\":[\"\",\"\"],\"windgust_speed\":[\"\",\"\"],\"outside_humidity\":[\"77\",\"%\"],\"sunrise\":\"08:13:00\",\"sunset\":\"17:56:00\",\"diffday\":3,\"moon_age\":17.9,\"moon_phase\":\"Lune gibbeuse d\\u00e9croissante\"}"],"182246":[75101,"{\"town\":\"Paris 1er Arrondissement\",\"update\":\"2026-02-05T16:10:25+01:00\",\"datetime\":\"2026-02-05T19:00:00+0100\",\"rr10\":0.6,\"rr1\":0.8,\"weather\":10,\"temp2m\":11,\"wind10m\":10,\"gust10m\":33,\"dirwind10m\":118,\"probarain\":90,\"probafog\":10,\"probafrost\":0,\"probawind70\":0,\"probawind100\":0,\"gustx\":33,\"iso0\":\"\",\"datetime_1\":\"2026-02-06T19:00:00+0100\",\"rr10_1\":0,\"rr1_1\":0,\"weather_1\":40,\"temp2m_1\":10,\"wind10m_1\":10,\"gust10m_1\":37,\"dirwind10m_1\":226,\"probarain_1\":50,\"probafog_1\":0,\"probafrost_1\":0,\"probawind70_1\":0,\"probawind100_1\":0,\"gustx_1\":37,\"iso0_1\":\"\",\"station\":\"Paris (75)\",\"temperature\":[\"10.4\",\"\\u00b0C\"],\"barometer\":[\"983.1\",\"hPa\"],\"rainfall\":[\"0.0\",\"mm\"],\"solar_radiation\":[\"0\",\"W\/m\\u00b2\"],\"wind_speed\":[\"24.1\",\"km\/h\"],\"windchill\":[\"\",\"\"],\"windgust_speed\":[\"\",\"\"],\"outside_humidity\":[\"86\",\"%\"],\"sunrise\":\"08:13:00\",\"sunset\":\"17:56:00\",\"diffday\":3,\"moon_age\":17.9,\"moon_phase\":\"Lune gibbeuse d\\u00e9croissante\"}"],"190619":[75101,"{\"town\":\"Paris 1er Arrondissement\",\"update\":\"2026-02-05T16:10:25+01:00\",\"datetime\":\"2026-02-05T19:00:00+0100\",\"rr10\":0.6,\"rr1\":0.8,\"weather\":10,\"temp2m\":11,\"wind10m\":10,\"gust10m\":33,\"dirwind10m\":118,\"probarain\":90,\"probafog\":10,\"probafrost\":0,\"probawind70\":0,\"probawind100\":0,\"gustx\":33,\"iso0\":\"\",\"datetime_1\":\"2026-02-06T19:00:00+0100\",\"rr10_1\":0,\"rr1_1\":0,\"weather_1\":40,\"temp2m_1\":10,\"wind10m_1\":10,\"gust10m_1\":37,\"dirwind10m_1\":226,\"probarain_1\":50,\"probafog_1\":0,\"probafrost_1\":0,\"probawind70_1\":0,\"probawind100_1\":0,\"gustx_1\":37,\"iso0_1\":\"\",\"station\":\"Paris (75)\",\"temperature\":[\"10.5\",\"\\u00b0C\"],\"barometer\":[\"983.4\",\"hPa\"],\"rainfall\":[\"0.0\",\"mm\"],\"solar_radiation\":[\"0\",\"W\/m\\u00b2\"],\"wind_speed\":[\"20.9\",\"km\/h\"],\"windchill\":[\"\",\"\"],\"windgust_speed\":[\"\",\"\"],\"outside_humidity\":[\"85\",\"%\"],\"sunrise\":\"08:13:00\",\"sunset\":\"17:56:00\",\"diffday\":3,\"moon_age\":17.9,\"moon_phase\":\"Lune gibbeuse d\\u00e9croissante\"}"],"202740":[75101,"{\"town\":\"Paris 1er Arrondissement\",\"update\":\"2026-02-05T16:10:25+01:00\",\"datetime\":\"2026-02-05T19:00:00+0100\",\"rr10\":0.6,\"rr1\":0.8,\"weather\":10,\"temp2m\":11,\"wind10m\":10,\"gust10m\":33,\"dirwind10m\":118,\"probarain\":90,\"probafog\":10,\"probafrost\":0,\"probawind70\":0,\"probawind100\":0,\"gustx\":33,\"iso0\":\"\",\"datetime_1\":\"2026-02-06T19:00:00+0100\",\"rr10_1\":0,\"rr1_1\":0,\"weather_1\":40,\"temp2m_1\":10,\"wind10m_1\":10,\"gust10m_1\":37,\"dirwind10m_1\":226,\"probarain_1\":50,\"probafog_1\":0,\"probafrost_1\":0,\"probawind70_1\":0,\"probawind100_1\":0,\"gustx_1\":37,\"iso0_1\":\"\",\"station\":\"Paris (75)\",\"temperature\":[\"10.1\",\"\\u00b0C\"],\"barometer\":[\"983.2\",\"hPa\"],\"rainfall\":[\"0.0\",\"mm\"],\"solar_radiation\":[\"0\",\"W\/m\\u00b2\"],\"wind_speed\":[\"24.8\",\"km\/h\"],\"windchill\":[\"\",\"\"],\"windgust_speed\":[\"\",\"\"],\"outside_humidity\":[\"88\",\"%\"],\"sunrise\":\"08:13:00\",\"sunset\":\"17:56:00\",\"diffday\":3,\"moon_age\":17.9,\"moon_phase\":\"Lune gibbeuse d\\u00e9croissante\"}"],"204418":["92012","{\"town\":\"Boulogne-Billancourt\",\"update\":\"2026-02-05T16:10:25+01:00\",\"datetime\":\"2026-02-05T19:00:00+0100\",\"rr10\":0.7,\"rr1\":1,\"weather\":10,\"temp2m\":11,\"wind10m\":10,\"gust10m\":33,\"dirwind10m\":117,\"probarain\":100,\"probafog\":10,\"probafrost\":0,\"probawind70\":0,\"probawind100\":0,\"gustx\":33,\"iso0\":\"\",\"datetime_1\":\"2026-02-06T19:00:00+0100\",\"rr10_1\":0,\"rr1_1\":0,\"weather_1\":40,\"temp2m_1\":9,\"wind10m_1\":15,\"gust10m_1\":45,\"dirwind10m_1\":229,\"probarain_1\":50,\"probafog_1\":0,\"probafrost_1\":0,\"probawind70_1\":0,\"probawind100_1\":0,\"gustx_1\":45,\"iso0_1\":\"\",\"station\":\"Paris (75)\",\"temperature\":[\"10.1\",\"\\u00b0C\"],\"barometer\":[\"983.3\",\"hPa\"],\"rainfall\":[\"0.0\",\"mm\"],\"solar_radiation\":[\"0\",\"W\\\/m\\u00b2\"],\"wind_speed\":[\"27.7\",\"km\\\/h\"],\"windchill\":[\"\",\"\"],\"windgust_speed\":[\"\",\"\"],\"outside_humidity\":[\"89\",\"%\"],\"sunrise\":\"08:13:00\",\"sunset\":\"17:56:00\",\"diffday\":3,\"moon_age\":17.9,\"moon_phase\":\"Lune gibbeuse d\\u00e9croissante\"}"]}